itsxpress/__init__.py
itsxpress/definitions.py
itsxpress/main.py
itsxpress/ITSx_db/HMMs/A.hmm
itsxpress/ITSx_db/HMMs/B.hmm
itsxpress/ITSx_db/HMMs/C.hmm
itsxpress/ITSx_db/HMMs/D.hmm
itsxpress/ITSx_db/HMMs/E.hmm
itsxpress/ITSx_db/HMMs/F.hmm
itsxpress/ITSx_db/HMMs/G.hmm
itsxpress/ITSx_db/HMMs/H.hmm
itsxpress/ITSx_db/HMMs/I.hmm
itsxpress/ITSx_db/HMMs/L.hmm
itsxpress/ITSx_db/HMMs/M.hmm
itsxpress/ITSx_db/HMMs/O.hmm
itsxpress/ITSx_db/HMMs/P.hmm
itsxpress/ITSx_db/HMMs/Q.hmm
itsxpress/ITSx_db/HMMs/R.hmm
itsxpress/ITSx_db/HMMs/S.hmm
itsxpress/ITSx_db/HMMs/T.hmm
itsxpress/ITSx_db/HMMs/U.hmm
itsxpress/ITSx_db/HMMs/all.hmm
itsxpress-1.8.1.dist-info/LICENSE.txt
itsxpress-1.8.1.dist-info/METADATA
itsxpress-1.8.1.dist-info/WHEEL
itsxpress-1.8.1.dist-info/entry_points.txt
itsxpress-1.8.1.dist-info/top_level.txt
itsxpress-1.8.1.dist-info/RECORD
