Metadata-Version: 2.1
Name: itsxpress
Version: 1.8.1
Summary: Rapidly trim sequences down to their Internally Transcribed Spacer ITS regions
Author-email: "Adam R. Rivers" <adam.rivers@usda.gov>, "Sveinn V. Einarsson" <seinarsson@ufl.edu>
Maintainer-email: "Adam R. Rivers" <adam.rivers@usda.gov>, "Sveinn V. Einarsson" <seinarsson@ufl.edu>
License: Creative Commons Legal Code CC0 1.0 Universal Official translations of this
Project-URL: repository, http://github.com/usda-ars-gbru/itsxpress
Keywords: Amplicon,sequencing,fungal,ITS
Classifier: Topic :: Scientific/Engineering :: Bio-Informatics
Classifier: Programming Language :: Python :: 3.6
Classifier: Programming Language :: Python :: 3.5
Classifier: Development Status :: 3 - Alpha
Requires-Python: >=3.5
License-File: LICENSE.txt
Requires-Dist: biopython (>=1.79)
Requires-Dist: pyzstd (>=0.15.3)
Provides-Extra: tests
Requires-Dist: pytest ; extra == 'tests'
